{
  "responses": {
    "accept": [
      "accept",
      "yes",
      "y",
      "a"
    ],
    "decline": [
      "decline",
      "no",
      "n",
      "d"
    ],
    "flinger": [
      "flinger",
      "fli",
      "f"
    ],
    "token": [
      "token",
      "tok",
      "t"
    ],
    "scroll": [
      "scroll",
      "scr",
      "s"
    ],
    "gaser": [
      "gaser",
      "gas",
      "g"
    ]

  },
  "chars": {
    "mazei": [
      "mazei",
      "maz",
      "m"
    ],
    "indara": [
      "indara",
      "ind",
      "in",
      "i"
    ]
  }
}
